splurge_safe_io/__init__.py
splurge_safe_io/constants.py
splurge_safe_io/exceptions.py
splurge_safe_io/path_validator.py
splurge_safe_io/safe_text_file_reader.py
splurge_safe_io/safe_text_file_writer.py
splurge_safe_io-2025.1.1.dist-info/licenses/LICENSE
splurge_safe_io-2025.1.1.dist-info/METADATA
splurge_safe_io-2025.1.1.dist-info/WHEEL
splurge_safe_io-2025.1.1.dist-info/entry_points.txt
splurge_safe_io-2025.1.1.dist-info/top_level.txt
splurge_safe_io-2025.1.1.dist-info/RECORD
