Metadata-Version: 2.4
Name: splurge-safe-io
Version: 2025.1.1
Summary: A safe, atomic, and cross-platform way to handle text file I/O in Python.
Author: Jim Schilling
License-Expression: MIT
Project-URL: Homepage, https://github.com/jim-schilling/splurge-safe-io
Project-URL: Repository, https://github.com/jim-schilling/splurge-safe-io
Project-URL: Documentation, https://github.com/jim-schilling/splurge-safe-io#readme
Project-URL: Bug Tracker, https://github.com/jim-schilling/splurge-safe-io/issues
Keywords: io,file,file-processing
Classifier: Development Status :: 3 - Alpha
Classifier: Intended Audience :: Developers
Classifier: Programming Language :: Python :: 3
Classifier: Programming Language :: Python :: 3.10
Classifier: Programming Language :: Python :: 3.11
Classifier: Programming Language :: Python :: 3.12
Classifier: Programming Language :: Python :: 3.13
Classifier: Topic :: Software Development :: Libraries :: Python Modules
Requires-Python: >=3.10
License-File: LICENSE
Provides-Extra: dev
Requires-Dist: pytest>=8.4.2; extra == "dev"
Requires-Dist: pytest-cov>=7.0.0; extra == "dev"
Requires-Dist: mypy>=1.18.2; extra == "dev"
Requires-Dist: ruff>=0.13.3; extra == "dev"
Requires-Dist: pytest-mock>=3.15.1; extra == "dev"
Requires-Dist: hypothesis>=6.140.3; extra == "dev"
Dynamic: license-file
